injectdep/__init__.py
injectdep/errors.py
injectdep/module.py
injectdep-0.0.1.dist-info/METADATA
injectdep-0.0.1.dist-info/WHEEL
injectdep-0.0.1.dist-info/top_level.txt
injectdep-0.0.1.dist-info/RECORD
