Metadata-Version: 2.1
Name: injectdep
Version: 0.0.1
Summary: Injección de dependencias para python
Home-page: https://github.com/jbuendia1y/py-injectdep
Author: jbuendia1y - jbuendia1y@gmail.com
Author-email: jbuendia1y@gmail.com
Keywords: python,injection,dependency,jbuendia1y,library
